pdfcc/__init__.py
pdfcc/logger.py
pdfcc/pdfcc.py
PdfCC-1.0.0.dist-info/LICENSE
PdfCC-1.0.0.dist-info/METADATA
PdfCC-1.0.0.dist-info/WHEEL
PdfCC-1.0.0.dist-info/entry_points.txt
PdfCC-1.0.0.dist-info/top_level.txt
PdfCC-1.0.0.dist-info/RECORD
